confeasy/__init__.py
confeasy/cmdline.py
confeasy/envars.py
confeasy/inifile.py
confeasy/jsonfile.py
confeasy/tomlfile.py
confeasy-1.0.0.dist-info/LICENSE
confeasy-1.0.0.dist-info/METADATA
confeasy-1.0.0.dist-info/WHEEL
confeasy-1.0.0.dist-info/RECORD
