Metadata-Version: 2.1
Name: confeasy
Version: 1.0.0
Summary: Application configuration inspired by Microsoft.Extensions.Configuration (.NET).
Home-page: https://github.com/jdvor/confeasy
License: MIT
Keywords: configuration,json,environment variables,command line
Author: jan Dvorak
Author-email: jandvorak.public@gmail.com
Requires-Python: >=3.12,<4.0
Classifier: License :: OSI Approved :: MIT License
Classifier: Programming Language :: Python :: 3
Classifier: Programming Language :: Python :: 3.12
Classifier: Programming Language :: Python :: 3.13
Project-URL: Bug Tracker, https://github.com/jdvor/confeasy/issues
Project-URL: Repository, https://github.com/jdvor/confeasy
